{
   "type":"object",
   "title":"job",
   "properties":{
      "name":{
         "type":"string",
         "title":"name"
      },
      "sources":{
         "type":"array",
         "title":"sources",
         "format":"tabs",
         "items":{
            "title":"source",
            "headerTemplate":"{{i}} - {{self.name}}",
            "oneOf":[
               {
                  "title":"Fixed",
                  "type":"object",
                  "properties":{
                     "name":{
                        "type":"string",
                        "title":"name"
                     },
                     "urls":{
                        "type":"array",
                        "title":"urls",
                        "uniqueItems":true,
                        "format":"table",
                        "items":{
                           "type":"string",
                           "title":"url"
                        }
                     },
                     "type":{
                        "type":"string",
                        "title":"type",
                        "default":"fixed",
                        "options":{
                           "hidden":true
                        }
                     }
                  }
               },
               {
                  "title":"Jdbc",
                  "properties":{
                     "name":{
                        "type":"string",
                        "title":"name"
                     },
                     "query":{
                        "type":"string",
                        "title":"query"
                     },
                     "type":{
                        "type":"string",
                        "title":"type",
                        "default":"jdbc",
                        "options":{
                           "hidden":true
                        }
                     },
                     "url":{
                        "type":"string",
                        "title":"url"
                     }
                  }
               },
               {
                  "title":"Csv",
                  "properties":{
                     "name":{
                        "type":"string",
                        "title":"name"
                     },
                     "files":{
                        "type":"array",
                        "title":"files",
                        "uniqueItems":true,
                        "format":"table",
                        "items":{
                           "type":"string",
                           "title":"file"
                        }
                     },
                     "type":{
                        "type":"string",
                        "title":"type",
                        "default":"csv",
                        "options":{
                           "hidden":true
                        }
                     }
                  }
               },
               {
                  "title":"RobotsTxt",
                  "properties":{
                     "name":{
                        "type":"string",
                        "title":"name"
                     },
                     "robots_txt":{
                        "type":"string",
                        "title":"robots_txt"
                     },
                     "max_depth":{
                        "type":"integer",
                        "title":"max_depth"
                     },
                     "type":{
                        "type":"string",
                        "title":"type",
                        "default":"robots_txt",
                        "options":{
                           "hidden":true
                        }
                     }
                  }
               }
            ]
         }
      },
      "stores":{
         "type":"object",
         "title":"stores",
         "properties":{
            "metadata":{
               "title":"metadata",
               "oneOf":[
                  {
                     "title":"Mongo Store",
                     "type":"object",
                     "properties":{
                        "type":{
                           "type":"string",
                           "title":"type",
                           "default":"mongo",
                           "options":{
                              "hidden":true
                           }
                        },
                        "uri":{
                           "type":"string",
                           "title":"uri"
                        },
                        "database":{
                           "type":"string",
                           "title":"database"
                        },
                        "bucket":{
                           "type":"string",
                           "title":"bucket"
                        },
                        "batch_size":{
                           "type":"number",
                           "title":"batch_size"
                        }
                     }
                  }
               ]
            },
            "blob":{
               "title":"Data store",
               "oneOf":[
                  {
                     "title":"Mongo Store",
                     "type":"object",
                     "properties":{
                        "type":{
                           "type":"string",
                           "title":"type",
                           "default":"mongo",
                           "options":{
                              "hidden":true
                           }
                        },
                        "uri":{
                           "type":"string",
                           "title":"uri"
                        },
                        "database":{
                           "type":"string",
                           "title":"database"
                        },
                        "bucket":{
                           "type":"string",
                           "title":"bucket"
                        },
                        "batch_size":{
                           "type":"number",
                           "title":"batch_size"
                        }
                     }
                  }
               ]
            }
         }
      },
      "filters":{
         "type":"object",
         "title":"filters",
         "properties":{
            "links":{
               "title":"links",
               "type":"object",
               "properties":{
                  "type":{
                     "type":"string",
                     "title":"type",
                     "default":"query",
                     "options":{
                        "hidden":true
                     }
                  },
                  "value":{
                     "type":"string",
                     "title":"value"
                  }
               }
            }
         }
      },
      "extractors":{
         "type":"object",
         "title":"extractors",
         "properties":{
            "pages":{
               "type":"array",
               "title":"pages",
               "format":"tabs",
               "items":{
                  "type":"object",
                  "headerTemplate":"{{i}} - {{self.name}}",
                  "title":"page",
                  "properties":{
                     "key_field":{
                        "type":"string",
                        "title":"key_field"
                     },
                     "name":{
                        "type":"string",
                        "title":"name"
                     },
                     "multiple":{
                        "title":"multiple",
                        "type":"object",
                        "properties":{
                           "source":{
                              "type":"string",
                              "title":"source",
                              "enum":[
                                 "EMPTY",
                                 "BODY",
                                 "HEADERS",
                                 "URL",
                                 "COOKIE"
                              ]
                           },
                           "type":{
                              "type":"string",
                              "title":"type"
                           },
                           "value":{
                              "type":"string",
                              "title":"value"
                           }
                        }
                     },
                     "store":{
                        "title":"store",
                        "oneOf":[
                           {
                              "title":"Mongo Store",
                              "type":"object",
                              "properties":{
                                 "type":{
                                    "type":"string",
                                    "title":"type",
                                    "default":"mongo",
                                    "options":{
                                       "hidden":true
                                    }
                                 },
                                 "uri":{
                                    "type":"string",
                                    "title":"uri"
                                 },
                                 "database":{
                                    "type":"string",
                                    "title":"database"
                                 },
                                 "bucket":{
                                    "type":"string",
                                    "title":"bucket"
                                 },
                                 "batch_size":{
                                    "type":"number",
                                    "title":"batch_size"
                                 }
                              }
                           }
                        ]
                     },
                     "links":{
                        "title":"links",
                        "type":"object",
                        "properties":{
                           "type":{
                              "type":"string",
                              "title":"type",
                              "default":"query",
                              "options":{
                                 "hidden":true
                              }
                           },
                           "value":{
                              "type":"string",
                              "title":"value"
                           }
                        }
                     },
                     "fields":{
                        "type":"array",
                        "title":"fields",
                        "items":{
                           "type":"object",
                           "title":"field",
                           "properties":{
                              "first_only":{
                                 "type":"boolean",
                                 "title":"first_only",
                                 "default":true
                              },
                              "name":{
                                 "type":"string",
                                 "title":"name"
                              },
                              "extractor":{
                                 "title":"extractor",
                                 "type":"object",
                                 "properties":{
                                    "source":{
                                       "type":"string",
                                       "title":"source",
                                       "enum":[
                                          "EMPTY",
                                          "BODY",
                                          "HEADERS",
                                          "URL",
                                          "COOKIE"
                                       ]
                                    },
                                    "type":{
                                       "type":"string",
                                       "title":"type"
                                    },
                                    "value":{
                                       "type":"string",
                                       "title":"value"
                                    }
                                 }
                              },
                              "use_multiple":{
                                 "type":"boolean",
                                 "title":"use_multiple",
                                 "default":false
                              }
                           }
                        }
                     }
                  }
               }
            },
            "outlinks":{
               "type":"array",
               "title":"outlinks",
               "format":"tabs",
               "items":{
                  "type":"object",
                  "headerTemplate":"{{i}} - {{self.name}}",
                  "title":"outlink",
                  "properties":{
                     "name":{
                        "type":"string",
                        "title":"name"
                     },
                     "extractor":{
                        "title":"extractor",
                        "type":"object",
                        "properties":{
                           "source":{
                              "type":"string",
                              "title":"source",
                              "enum":[
                                 "EMPTY",
                                 "BODY",
                                 "HEADERS",
                                 "URL",
                                 "COOKIE"
                              ]
                           },
                           "type":{
                              "type":"string",
                              "title":"type"
                           },
                           "value":{
                              "type":"string",
                              "title":"value"
                           }
                        }
                     }
                  }
               }
            }
         }
      }
   }
}